HISTORY.rst
LICENSE
LICENSE.rst
MANIFEST.in
README.rst
requirements.txt
setup.cfg
setup.py
test-requirements.txt
Flask_Multi_Redis.egg-info/PKG-INFO
Flask_Multi_Redis.egg-info/SOURCES.txt
Flask_Multi_Redis.egg-info/dependency_links.txt
Flask_Multi_Redis.egg-info/not-zip-safe
Flask_Multi_Redis.egg-info/requires.txt
Flask_Multi_Redis.egg-info/top_level.txt
flask_multi_redis/__init__.py
flask_multi_redis/aggregator.py
flask_multi_redis/main.py
flask_multi_redis/redis_node.py